[
  {
    "date": "2026-06-21",
    "stocks": {
      "KOSPI": {
        "close": 9052.42,
        "change": -11.42,
        "pct": -0.13
      },
      "KOSDAQ": {
        "close": 966.59,
        "change": -34.34,
        "pct": -3.43
      },
      "SP500": {
        "close": 7500.58,
        "change": 80.48,
        "pct": 1.08
      },
      "NASDAQ": {
        "close": 26517.93,
        "change": 496.27,
        "pct": 1.91
      },
      "DOW": {
        "close": 51564.7,
        "change": 72.15,
        "pct": 0.14
      }
    },
    "fx": {
      "USD_KRW": 1531.004518,
      "JPY_KRW": 9.5
    },
    "news": {
      "economy": [
        {
          "title": "“증시로 떠나는 돈 붙잡아라”…공제회, 4%대 금리로 회원 자금 방어",
          "desc": "“증시로 떠나는 돈 붙잡아라”…공제회, 4%대 금리로 회원 자금 방어 한국경제"
        },
        {
          "title": "연준 매파적 동결에 美 증시 약세 [글로벌 머니플로우]",
          "desc": "연준 매파적 동결에 美 증시 약세 [글로벌 머니플로우] v.daum.net"
        },
        {
          "title": "기름값·금리·증시 다 움직인다… 19일 미·이란 서명이 바꿀 한국 경제 4가지 [중동전쟁]",
          "desc": "기름값·금리·증시 다 움직인다… 19일 미·이란 서명이 바꿀 한국 경제 4가지 [중동전쟁] 솔루션뉴스"
        },
        {
          "title": "日, 기준금리 1.0%로 인상...31년만에 최고",
          "desc": "日, 기준금리 1.0%로 인상...31년만에 최고 한국경제TV"
        },
        {
          "title": "증권사도 발행어음 금리 경쟁…우리투자증권 \"최대 연 3.7%\"",
          "desc": "증권사도 발행어음 금리 경쟁…우리투자증권 \"최대 연 3.7%\" 한국경제"
        },
        {
          "title": "[펜앤특집: 지방선거 이후 한국경제] 증시, 부동산, 거시경제 모두 \"불안 산적해\"",
          "desc": "[펜앤특집: 지방선거 이후 한국경제] 증시, 부동산, 거시경제 모두 \"불안 산적해\" 펜앤마이크"
        }
      ],
      "realestate": [
        {
          "title": "상승폭 둔화했지만… 매매든 전세든 서울 아파트 가격 또 올랐다 [주말 Q&A]",
          "desc": "상승폭 둔화했지만… 매매든 전세든 서울 아파트 가격 또 올랐다 [주말 Q&A] 더스쿠프"
        },
        {
          "title": "인천 아파트 거래 늘었지만 집값은 제자리",
          "desc": "인천 아파트 거래 늘었지만 집값은 제자리 인천일보"
        },
        {
          "title": "[부동산] 서울 아파트 확실한 상승세",
          "desc": "[부동산] 서울 아파트 확실한 상승세 starnewskorea.com"
        },
        {
          "title": "[6월 3주] 충남 아파트값 나홀로 하락...대전·세종은 상승",
          "desc": "[6월 3주] 충남 아파트값 나홀로 하락...대전·세종은 상승 충남일보"
        },
        {
          "title": "삼전닉스가 부동산 시장도 흔드나…화성 동탄 아파트 1주새 2.22%↑",
          "desc": "삼전닉스가 부동산 시장도 흔드나…화성 동탄 아파트 1주새 2.22%↑ 디지털데일리"
        },
        {
          "title": "부동산원, 6월 3주 주간 아파트가격 동향",
          "desc": "부동산원, 6월 3주 주간 아파트가격 동향 경남대학교 교육방송국"
        }
      ],
      "global": [
        {
          "title": "[글로벌 포커스] 이란전쟁이 키운 지정학의 변동성",
          "desc": "[글로벌 포커스] 이란전쟁이 키운 지정학의 변동성 중앙일보"
        },
        {
          "title": "무역 흑자 1조달러 시대…세계 지정학의 변수 된 중국의 수출과 경제 개혁",
          "desc": "무역 흑자 1조달러 시대…세계 지정학의 변수 된 중국의 수출과 경제 개혁 주간경향"
        },
        {
          "title": "지정학이 글로벌 기업의 경영을 뒤흔든다",
          "desc": "지정학이 글로벌 기업의 경영을 뒤흔든다 pado.kr"
        },
        {
          "title": "[외신 에스프레소] 스페이스X·오픈AI '상장 광풍'…지정학 위기 속 요동치는 글로벌 경제",
          "desc": "[외신 에스프레소] 스페이스X·오픈AI '상장 광풍'…지정학 위기 속 요동치는 글로벌 경제 한국경제"
        },
        {
          "title": "AI 기회 맞은 신흥국의 도약…AI가 새로운 글로벌 경제 지도 만든다",
          "desc": "AI 기회 맞은 신흥국의 도약…AI가 새로운 글로벌 경제 지도 만든다 아이티데일리"
        },
        {
          "title": "[채인택 칼럼] COP30 가로막은 6대 지정학 장벽...이상과 현실의 간극 확인",
          "desc": "[채인택 칼럼] COP30 가로막은 6대 지정학 장벽...이상과 현실의 간극 확인 ESG경제"
        }
      ],
      "usnews": [
        {
          "title": "중동 전쟁 확전 시 국제유가 ‘174달러’…환율 1500원대 장기화 가능성도",
          "desc": "중동 전쟁 확전 시 국제유가 ‘174달러’…환율 1500원대 장기화 가능성도 농민신문"
        },
        {
          "title": "국제유가 급등에…원-달러 환율 1500원 훌쩍 넘어",
          "desc": "국제유가 급등에…원-달러 환율 1500원 훌쩍 넘어 한겨레"
        },
        {
          "title": "[환율 전망] 이제는 놀랍지 않은 1,500원",
          "desc": "[환율 전망] 이제는 놀랍지 않은 1,500원 KB Think"
        },
        {
          "title": "미국·이란 협상 교착에 국제유가 100달러 돌파",
          "desc": "미국·이란 협상 교착에 국제유가 100달러 돌파 중기이코노미"
        },
        {
          "title": "내려올 줄 모르는 국제 유가…4거래일 연속 배럴당 100달러 웃돌았다",
          "desc": "내려올 줄 모르는 국제 유가…4거래일 연속 배럴당 100달러 웃돌았다 조선일보"
        },
        {
          "title": "트럼프의 이란 전쟁…세계 경제 ‘에너지 쇼크’ 경고 커진다 [이슈+]",
          "desc": "트럼프의 이란 전쟁…세계 경제 ‘에너지 쇼크’ 경고 커진다 [이슈+] 에너지경제신문"
        }
      ]
    },
    "portfolio": {
      "holdings": [
        {
          "ticker": "JOBY",
          "name": "조비 에비에이션",
          "shares": 243.401791,
          "avg_price": 10.73,
          "current_price": 10.0,
          "value": 2434.01791,
          "cost": 2611.7012174300003,
          "pnl": -177.68330743000024,
          "pnl_pct": -6.803355079217156
        },
        {
          "ticker": "QQQ",
          "name": "QQQ",
          "shares": 2.916851,
          "avg_price": 627.49,
          "current_price": 740.62,
          "value": 2160.2781876199997,
          "cost": 1830.29483399,
          "pnl": 329.9833536299998,
          "pnl_pct": 18.02897257326809
        },
        {
          "ticker": "GOOGL",
          "name": "알파벳 A",
          "shares": 5.214141,
          "avg_price": 282.56,
          "current_price": 368.03,
          "value": 1918.9603122299998,
          "cost": 1473.30768096,
          "pnl": 445.6526312699998,
          "pnl_pct": 30.248442808607006
        },
        {
          "ticker": "BLDR",
          "name": "빌더스 퍼스트소스",
          "shares": 11.69439,
          "avg_price": 92.22,
          "current_price": 80.59,
          "value": 942.4508901,
          "cost": 1078.4566458,
          "pnl": -136.0057556999999,
          "pnl_pct": -12.61114725656039
        },
        {
          "ticker": "NOW",
          "name": "서비스나우",
          "shares": 1.0,
          "avg_price": 106.55,
          "current_price": 95.04,
          "value": 95.04,
          "cost": 106.55,
          "pnl": -11.509999999999991,
          "pnl_pct": -10.802440168934764
        }
      ],
      "total_value": 7550.747299949999,
      "total_cost": 7100.31037818,
      "total_pnl": 450.43692176999866,
      "total_pnl_pct": 6.343904671466738
    }
  }
]